README.md
setup.py
linkpy/__init__.py
linkpy/linky_test.py
linkpy.egg-info/PKG-INFO
linkpy.egg-info/SOURCES.txt
linkpy.egg-info/dependency_links.txt
linkpy.egg-info/requires.txt
linkpy.egg-info/top_level.txt