Metadata-Version: 2.1
Name: linkpy
Version: 1.0
Summary: This module allows you to retrieve your Linky consumption data from your Enedis account.
Home-page: https://github.com/outadoc/linkindle
Author: Baptiste Candellier
Author-email: outadoc@gmail.com
License: GPLv3+
Project-URL: Bug Tracker, https://github.com/outadoc/linkindle/issues
Project-URL: Source Code, https://github.com/outadoc/linkindle
Keywords: linky enedis edf erdf pylinky linkindle energy meter linkpy
Platform: UNKNOWN
